error/__init__.py
error/exception_handler.py
com_terra_error-0.1.0.dist-info/METADATA
com_terra_error-0.1.0.dist-info/WHEEL
com_terra_error-0.1.0.dist-info/RECORD
